mrmd_pty/__init__.py
mrmd_pty/cli.py
mrmd_pty/server.py
mrmd_pty-0.1.1.dist-info/METADATA
mrmd_pty-0.1.1.dist-info/WHEEL
mrmd_pty-0.1.1.dist-info/entry_points.txt
mrmd_pty-0.1.1.dist-info/RECORD
